custa/__init__.py
custa/cli.py
custa/parser.py
custa/commands/build.py
custa/commands/init.py
custa/commands/serve.py
custa/project_template/custa.config.yaml
custa/project_template/content/404.cst
custa/project_template/content/index.cst
custa/project_template/themes/dark/css/base.css
custa/project_template/themes/dark/css/components.css
custa/project_template/themes/dark/css/navbar.css
custa/project_template/themes/dark/css/table.css
custa/project_template/themes/dark/images/logo.svg
custa/project_template/themes/dark/templates/base.html
custa/renderer/__init__.py
custa/renderer/base.py
custa/renderer/elements/__init__.py
custa/renderer/elements/button.py
custa/renderer/elements/headings.py
custa/renderer/elements/hr.py
custa/renderer/elements/section.py
custa/renderer/elements/text.py
custa/renderer/elements/lists/desc.py
custa/renderer/elements/lists/item.py
custa/renderer/elements/lists/list.py
custa/renderer/elements/lists/term.py
custa/renderer/elements/nav/nav_button.py
custa/renderer/elements/nav/nav_footer.py
custa/renderer/elements/nav/navbar.py
custa/renderer/elements/tables/table.py
custa/renderer/elements/tables/tbody.py
custa/renderer/elements/tables/td.py
custa/renderer/elements/tables/th.py
custa/renderer/elements/tables/thead.py
custa/renderer/elements/tables/tr.py
custa-0.1.6.dist-info/METADATA
custa-0.1.6.dist-info/WHEEL
custa-0.1.6.dist-info/entry_points.txt
custa-0.1.6.dist-info/top_level.txt
custa-0.1.6.dist-info/RECORD
