Metadata-Version: 2.4
Name: custa
Version: 0.1.6
Summary: Custom HTML generator from simple markup syntax
Author-email: ProPandaMen <propandamen@gmail.com>
License: MIT
Project-URL: Homepage, https://github.com/ProPandaMen/custa
Requires-Python: >=3.8
Requires-Dist: PyYAML>=6.0
Requires-Dist: typer>=0.15
